{
  "terms": {
    "+": "+",
    "-": "-",
    "*": "*",
    "/": "/",
    "%": "%",
    "^": "^",
    "(": "(",
    ")": ")",
    "{": "{",
    "}": "}",
    "<": "<",
    "<=": "<=",
    "=": "=",
    "==": "==",
    ">": ">",
    ">=": ">=",
    "<>": "<>",
    ";": ";",
    "&&" : "&&",
    "||" : "@|@|",
    "->": "->",
    "#": "#",
    ",": ",",
    "/*": "/@*",
    "id": "[A-Za-z@_]([A-Za-z@_0-9]+|empty)",
    "num": "[0-9]+",
    "realNum": "[0-9]+.[0-9]+(((E|e)(-|empty)[0-9]+)|empty)",
    "ch": "\'_\'",
    "empty": null
  },
  "keywords": ["class","true","false","if","else","while",
    "int","long","float","double","char","bool","void","not","def","return"
  ],
  "meta": {
    "mlCommentStart": "/*",
    "mlCommentEnd": "*/",
    "id": "id",
    "commentLine": "#",
    "operands": ["id","num","realNum","true","false","ch","UE","D"],
    "operators": ["<","<=",">",">=","==","<>","=","+","-","*","/","%","^","->","&&","||","if","while","class","def","return","um","up","if","while","FD","FL","F","SL","MH","MB"],
    "aliases": {
      "-": "um",
      "+": "up"
    }
  },
  "nonTerms": ["PROG","A","CMDS","CMD","FD","VDS","VD","DL","DS","D","MD","MH","MB","T","FPL","FL","F","SL","S","R","P","OP","J","B",
    "ES","EXPS","SE",
    "DISJ","CONJ","E","AE","RELOP","TE","FA","UE","PE","RE","CB"
  ],
  "productions": [{"PROG": ["class","id","{","CB","}"]},
    {"CB": "CMDS"},{"CB": "empty"},
    {"CMDS": ["CMDS","CMD"]},{"CMDS": "CMD"},
    {"CMD": "FD"},{"CMD": "MD"},
    {"FD": ["T","VDS",";"]},{"VDS": ["VDS",",","VD"]},{"VDS": "VD"},
    {"VD": ["id","=","B"]},{"VD": "id"},
    {"DL": ["T","DS",";"]},{"DS": ["DS",",","D"]},{"DS": "D"},
    {"D": ["id","=","B"]},{"D": "id"},{"T": "int"},{"T": "long"},{"T": "float"},{"T": "double"},{"T": "char"},
    {"T": "bool"},{"T": "void"},{"T": "id"},
    {"MD": ["MH","MB"]},{"MH": ["T","id","(","FPL",")"]},
    {"FPL": "FL"},{"FPL": "empty"},
    {"FL": ["FL",",","F"]},{"FL": "F"},
    {"MB": "R"},{"MB": ";"},
    {"F": ["T","id"]},{"P": "OP"},{"P": "R"},{"P": "J"},{"P": "ES"},{"P": "EXPS"},
    {"ES": ";"},{"EXPS": ["SE",";"]},
    {"SE": "A"},
    {"J": ["return","RE",";"]},{"RE": "B"},{"RE": "empty"},
    {"R": ["{","SL","}"]},
    {"SL": ["SL","S"]},{"SL": "S"},{"SL": "empty"},
    {"S": "DL"},{"S": "P"},
    {"OP": ["if","(","B",")","P"]},
    {"OP": ["if","(","B",")","P","else","P"]},
    {"OP": ["while","(","B",")","P"]},
    {"A": ["id","=","B"]},{"OP": "DL"},
    {"RELOP": "<"},{"RELOP": "<="},{"RELOP": ">"},{"RELOP": ">="},{"RELOP": "=="},{"RELOP": "<>"},
    {"B": ["B","->","DISJ"]},{"B": "DISJ"},
    {"DISJ": ["DISJ","||","CONJ"]},{"DISJ": "CONJ"},
    {"CONJ": ["CONJ","&&","E"]},{"CONJ": "E"},
    {"E": ["AE","RELOP","AE"]},{"E": "AE"},
    {"AE": ["AE","+","TE"]},{"AE": ["AE","-","TE"]},{"AE": "TE"},
    {"TE": ["TE","*","FA"]},{"TE": ["TE","/","FA"]},{"TE": ["TE","%","FA"]},{"TE": "FA"},
    {"FA": ["FA","^","UE"]},{"FA": "UE"},
    {"UE": ["um","UE"]},{"UE": ["up","UE"]},{"UE": "PE"},
    {"PE": "id"},{"PE": "num"},{"PE": "realNum"},{"PE": "true"},{"PE": "false"},{"PE": "ch"},
    {"PE": ["(","B",")"]},{"PE": ["not","(","B",")"]}
  ],
  "start": "PROG"
}